simplify.cpython-37m-darwin.so
quad_mesh_simplify-1.1.5.dist-info/LICENSE.txt
quad_mesh_simplify-1.1.5.dist-info/METADATA
quad_mesh_simplify-1.1.5.dist-info/WHEEL
quad_mesh_simplify-1.1.5.dist-info/top_level.txt
quad_mesh_simplify-1.1.5.dist-info/RECORD
