Metadata-Version: 2.1
Name: quad-mesh-simplify
Version: 1.1.5
Summary: Simplify meshes including vertex features.
Home-page: https://github.com/jannessm/quadric-mesh-simplification
Author: Jannes Magnusson
License: UNKNOWN
Platform: UNKNOWN
Requires-Python: >=3.6.3
License-File: LICENSE.txt
Requires-Dist: numpy
Requires-Dist: cython
